pycft-1.0.0.data/data/include/fmt/std.h
pycft-1.0.0.data/data/include/fmt/compile.h
pycft-1.0.0.data/data/include/fmt/ranges.h
pycft-1.0.0.data/data/include/fmt/os.h
pycft-1.0.0.data/data/include/fmt/xchar.h
pycft-1.0.0.data/data/include/fmt/printf.h
pycft-1.0.0.data/data/include/fmt/format-inl.h
pycft-1.0.0.data/data/include/fmt/format.h
pycft-1.0.0.data/data/include/fmt/ostream.h
pycft-1.0.0.data/data/include/fmt/args.h
pycft-1.0.0.data/data/include/fmt/chrono.h
pycft-1.0.0.data/data/include/fmt/core.h
pycft-1.0.0.data/data/include/fmt/base.h
pycft-1.0.0.data/data/include/fmt/color.h
pycft-1.0.0.data/data/lib/libfmt.a
pycft-1.0.0.data/data/lib/cmake/fmt/fmt-targets-release.cmake
pycft-1.0.0.data/data/lib/cmake/fmt/fmt-targets.cmake
pycft-1.0.0.data/data/lib/cmake/fmt/fmt-config.cmake
pycft-1.0.0.data/data/lib/cmake/fmt/fmt-config-version.cmake
pycft-1.0.0.data/data/lib/pkgconfig/fmt.pc
pycft.libs/libstdc++-0530927c.so.6.0.32
pycft.libs/libgcc_s-1257a076.so.1
pycft-1.0.0.dist-info/LICENSE
pycft-1.0.0.dist-info/WHEEL
pycft-1.0.0.dist-info/RECORD
pycft-1.0.0.dist-info/top_level.txt
pycft-1.0.0.dist-info/METADATA
pycft/set_cover_solver.py
pycft/_bindings.cpython-313-i386-linux-musl.so
pycft/__init__.py
