Metadata-Version: 2.2
Name: pycft
Version: 1.0.0
Summary: Python-Bindings for the C++-based Set Cover Algorithm CFT.
Author: Luca Accorsi, Francesco Cavaliere, and Dominik Krupke
License: MIT
Requires-Python: >=3.10
License-File: LICENSE
Dynamic: author
Dynamic: description
Dynamic: description-content-type
Dynamic: license
Dynamic: requires-python
Dynamic: summary
